{
  "type": "sparkfun-discretesemi-mosfet-nchannel-pth",
  "label": "MOSFET-NCHANNEL",
  "family": "sparkfun Mosfet (N Channel)",
  "description": "Generic NMOS footprint",
  "source": {
    "fzp": "sparkfun-discretesemi-mosfet-nchannel-pth.fzp",
    "moduleId": "SparkFun-DiscreteSemi-MOSFET-NCHANNEL-PTH"
  },
  "views": {
    "breadboard": {
      "svg": "<svg version=\"1.1\" baseProfile=\"tiny\" xmlns:svg=\"http://www.w3.org/2000/svg\" xmlns=\"http://www.w3.org/2000/svg\" x=\"0\" y=\"0\" viewBox=\"0 0 16.527 24.08\"><g id=\"breadboard\"><rect id=\"connector0pin\" x=\"0\" y=\"23\" fill=\"none\" width=\"2.16\" height=\"1\"/><rect id=\"connector1pin\" x=\"7.181\" y=\"23\" fill=\"none\" width=\"2.16\" height=\"1\"/><rect id=\"connector2pin\" x=\"14.367\" y=\"23\" fill=\"none\" width=\"2.16\" height=\"1\"/><line id=\"connector0leg\" stroke-linecap=\"round\" x1=\"1.08\" y1=\"24.08\" x2=\"1.08\" y2=\"31.259\" stroke=\"#8C8C8C\" fill=\"none\" stroke-width=\"2.16\"/><line id=\"connector1leg\" stroke-linecap=\"round\" x1=\"8.261\" y1=\"24.08\" x2=\"8.261\" y2=\"31.259\" stroke=\"#8C8C8C\" fill=\"none\" stroke-width=\"2.16\"/><line id=\"connector2leg\" stroke-linecap=\"round\" x1=\"15.447\" y1=\"24.08\" x2=\"15.447\" y2=\"31.259\" stroke=\"#8C8C8C\" fill=\"none\" stroke-width=\"2.16\"/><rect id=\"rect9506\" x=\"7.178\" y=\"14.731\" fill=\"#8C8C8C\" width=\"2.154\" height=\"9.35\"/><path id=\"path9510\" fill=\"#8C8C8C\" d=\"M3.287,14.731v3.316c0,0.424-0.782,1.059-1.198,1.425c-1.025,0.891-2.088,1.82-2.088,2.992   v1.619h2.154c0,0,0-1,0-1.209c0-0.518,0.904-1.389,1.35-1.77c0.997-0.869,1.945-1.689,1.945-2.748v-3.625H3.287L3.287,14.731z\"/><path id=\"path9514\" fill=\"#8C8C8C\" d=\"M13.221,14.731v3.316c0,0.424,0.781,1.059,1.199,1.425c1.027,0.891,2.089,1.82,2.089,2.992   v1.619h-2.154c0,0,0-1,0-1.209c0-0.518-0.904-1.389-1.35-1.77c-0.998-0.869-1.945-1.689-1.945-2.748v-3.625H13.221L13.221,14.731z\"/><rect id=\"rect9553\" x=\"1.615\" y=\"4.659\" fill=\"#1A1A1A\" width=\"13.278\" height=\"10.07\"/><path id=\"path9555\" fill=\"#141414\" d=\"M13.889,4.659v2.453v8.228v1.843c0.632-0.713,1.004-1.554,1.004-2.453l0,0V4.659H13.889z\"/><path id=\"path9557\" fill=\"#242424\" d=\"M2.621,4.659H1.616v10.07l0,0c0,0.899,0.373,1.74,1.005,2.453V15.34V7.112V4.659z\"/><path id=\"path9559\" fill=\"#1F1F1F\" d=\"M1.615,4.659L1.615,4.659c0,0.899,0.373,1.74,1.005,2.453h11.276   c0.632-0.713,1.005-1.554,1.005-2.453l0,0H1.615z\"/><path id=\"path9561\" fill=\"#141414\" d=\"M8.255,0C4.587,0,1.615,2.086,1.615,4.661h13.278C14.893,2.086,11.923,0,8.255,0z\"/><rect id=\"rect9563\" x=\"2.621\" y=\"7.112\" width=\"11.276\" height=\"10.07\"/><path fill=\"#999999\" d=\"M10.509,9.618h1.081v2.161h-1.081v1.079H7.27v1.08H5.11v-5.4h5.401L10.509,9.618L10.509,9.618z M9.43,9.618   H7.271v2.161H9.43V9.618z\"/></g></svg>",
      "w": 22.04,
      "h": 32.1,
      "pins": {
        "D": [
          1.44,
          31.33
        ],
        "G": [
          20.6,
          31.33
        ],
        "S": [
          11.01,
          31.33
        ]
      }
    },
    "schematic": {
      "svg": "<svg xmlns:svg=\"http://www.w3.org/2000/svg\" xmlns=\"http://www.w3.org/2000/svg\" version=\"1.2\" baseProfile=\"tiny\" x=\"0in\" y=\"0in\" viewBox=\"0 0 11.2487 10.4069\"><g id=\"schematic\"><circle class=\"other\" cx=\"7.74347\" cy=\"7.10847\" r=\"0.127\" stroke=\"#000000\" stroke-width=\"0.4064\" fill=\"none\"/><circle class=\"other\" cx=\"7.74347\" cy=\"3.29847\" r=\"0.127\" stroke=\"#000000\" stroke-width=\"0.4064\" fill=\"none\"/><rect class=\"other\" x=\"4.94947\" y=\"6.47347\" width=\"0.762\" height=\"1.27\" stroke=\"none\" stroke-width=\"0\" fill=\"#000000\" stroke-linecap=\"round\"/><rect class=\"other\" x=\"4.94947\" y=\"2.66347\" width=\"0.762\" height=\"1.27\" stroke=\"none\" stroke-width=\"0\" fill=\"#000000\" stroke-linecap=\"round\"/><rect class=\"other\" x=\"4.94947\" y=\"4.31447\" width=\"0.762\" height=\"1.778\" stroke=\"none\" stroke-width=\"0\" fill=\"#000000\" stroke-linecap=\"round\"/><line class=\"other\" x1=\"4.08587\" y1=\"2.79047\" x2=\"4.08587\" y2=\"7.74347\" stroke=\"#000000\" stroke-width=\"0.254\" stroke-linecap=\"round\"/><line class=\"other\" x1=\"7.74347\" y1=\"3.29847\" x2=\"5.73687\" y2=\"3.29847\" stroke=\"#000000\" stroke-width=\"0.1524\" stroke-linecap=\"round\"/><line class=\"other\" x1=\"7.74347\" y1=\"5.20347\" x2=\"7.74347\" y2=\"7.10847\" stroke=\"#000000\" stroke-width=\"0.1524\" stroke-linecap=\"round\"/><line class=\"other\" x1=\"5.71147\" y1=\"7.10847\" x2=\"7.74347\" y2=\"7.10847\" stroke=\"#000000\" stroke-width=\"0.1524\" stroke-linecap=\"round\"/><line class=\"other\" x1=\"7.74347\" y1=\"2.66347\" x2=\"7.74347\" y2=\"3.29847\" stroke=\"#000000\" stroke-width=\"0.1524\" stroke-linecap=\"round\"/><line class=\"other\" x1=\"7.74347\" y1=\"3.29847\" x2=\"10.2835\" y2=\"3.29847\" stroke=\"#000000\" stroke-width=\"0.1524\" stroke-linecap=\"round\"/><line class=\"other\" x1=\"10.2835\" y1=\"7.10847\" x2=\"7.74347\" y2=\"7.10847\" stroke=\"#000000\" stroke-width=\"0.1524\" stroke-linecap=\"round\"/><line class=\"other\" x1=\"7.74347\" y1=\"7.10847\" x2=\"7.74347\" y2=\"7.74347\" stroke=\"#000000\" stroke-width=\"0.1524\" stroke-linecap=\"round\"/><line class=\"other\" x1=\"3.93347\" y1=\"5.20347\" x2=\"2.66347\" y2=\"5.20347\" stroke=\"#000000\" stroke-width=\"0.1524\" stroke-linecap=\"round\"/><line class=\"other\" x1=\"5.71147\" y1=\"5.20347\" x2=\"6.98147\" y2=\"5.71147\" stroke=\"#000000\" stroke-width=\"0.1524\" stroke-linecap=\"round\"/><line class=\"other\" x1=\"6.98147\" y1=\"5.71147\" x2=\"6.98147\" y2=\"4.69547\" stroke=\"#000000\" stroke-width=\"0.1524\" stroke-linecap=\"round\"/><line class=\"other\" x1=\"6.98147\" y1=\"4.69547\" x2=\"5.71147\" y2=\"5.20347\" stroke=\"#000000\" stroke-width=\"0.1524\" stroke-linecap=\"round\"/><line class=\"other\" x1=\"6.85447\" y1=\"5.20347\" x2=\"7.74347\" y2=\"5.20347\" stroke=\"#000000\" stroke-width=\"0.1524\" stroke-linecap=\"round\"/><line class=\"other\" x1=\"6.85447\" y1=\"4.94947\" x2=\"5.96547\" y2=\"5.20347\" stroke=\"#000000\" stroke-width=\"0.3048\" stroke-linecap=\"round\"/><line class=\"other\" x1=\"5.96547\" y1=\"5.20347\" x2=\"6.85447\" y2=\"5.45747\" stroke=\"#000000\" stroke-width=\"0.3048\" stroke-linecap=\"round\"/><line class=\"other\" x1=\"6.85447\" y1=\"5.45747\" x2=\"6.85447\" y2=\"5.20347\" stroke=\"#000000\" stroke-width=\"0.3048\" stroke-linecap=\"round\"/><line class=\"other\" x1=\"6.85447\" y1=\"5.20347\" x2=\"6.60047\" y2=\"5.20347\" stroke=\"#000000\" stroke-width=\"0.3048\" stroke-linecap=\"round\"/><line class=\"other\" x1=\"10.2835\" y1=\"3.29847\" x2=\"10.2835\" y2=\"4.44147\" stroke=\"#000000\" stroke-width=\"0.1524\" stroke-linecap=\"round\"/><line class=\"other\" x1=\"10.2835\" y1=\"4.44147\" x2=\"10.2835\" y2=\"7.10847\" stroke=\"#000000\" stroke-width=\"0.1524\" stroke-linecap=\"round\"/><line class=\"other\" x1=\"10.2835\" y1=\"4.44147\" x2=\"9.64847\" y2=\"5.83847\" stroke=\"#000000\" stroke-width=\"0.1524\" stroke-linecap=\"round\"/><line class=\"other\" x1=\"9.64847\" y1=\"5.83847\" x2=\"10.9185\" y2=\"5.83847\" stroke=\"#000000\" stroke-width=\"0.1524\" stroke-linecap=\"round\"/><line class=\"other\" x1=\"10.9185\" y1=\"5.83847\" x2=\"10.2835\" y2=\"4.44147\" stroke=\"#000000\" stroke-width=\"0.1524\" stroke-linecap=\"round\"/><line class=\"other\" x1=\"9.64847\" y1=\"4.44147\" x2=\"10.2835\" y2=\"4.44147\" stroke=\"#000000\" stroke-width=\"0.1524\" stroke-linecap=\"round\"/><line class=\"other\" x1=\"10.2835\" y1=\"4.44147\" x2=\"10.9185\" y2=\"4.44147\" stroke=\"#000000\" stroke-width=\"0.1524\" stroke-linecap=\"round\"/><line class=\"other\" x1=\"10.9185\" y1=\"4.44147\" x2=\"11.1725\" y2=\"4.18747\" stroke=\"#000000\" stroke-width=\"0.1524\" stroke-linecap=\"round\"/><line class=\"other\" x1=\"9.64847\" y1=\"4.44147\" x2=\"9.39447\" y2=\"4.69547\" stroke=\"#000000\" stroke-width=\"0.1524\" stroke-linecap=\"round\"/><line class=\"pin\" id=\"connector2pin\" connectorname=\"D\" x1=\"7.74347\" y1=\"0.123472\" x2=\"7.74347\" y2=\"2.66347\" stroke=\"#787878\" stroke-width=\"0.246944\" stroke-linecap=\"round\"/><rect class=\"terminal\" id=\"connector2terminal\" x=\"7.74347\" y=\"0.123472\" width=\"0.0001\" height=\"0.0001\" stroke=\"none\" stroke-width=\"0\" fill=\"none\"/><g transform=\"translate(7.37306,1.39347)\"><g transform=\"rotate(270)\"><text class=\"text\" font-family=\"'Droid Sans'\" stroke=\"none\" stroke-width=\"0\" fill=\"#8c8c8c\" font-size=\"0.881944\" x=\"0\" y=\"0\" text-anchor=\"middle\">3</text></g></g><line class=\"pin\" id=\"connector0pin\" connectorname=\"G\" x1=\"0.123472\" y1=\"5.20347\" x2=\"2.66347\" y2=\"5.20347\" stroke=\"#787878\" stroke-width=\"0.246944\" stroke-linecap=\"round\"/><rect class=\"terminal\" id=\"connector0terminal\" x=\"0.123472\" y=\"5.20347\" width=\"0.0001\" height=\"0.0001\" stroke=\"none\" stroke-width=\"0\" fill=\"none\"/><text class=\"text\" font-family=\"'Droid Sans'\" stroke=\"none\" stroke-width=\"0\" fill=\"#8c8c8c\" font-size=\"0.881944\" x=\"1.39347\" y=\"4.83306\" text-anchor=\"middle\">1</text><line class=\"pin\" id=\"connector1pin\" connectorname=\"S\" x1=\"7.74347\" y1=\"10.2835\" x2=\"7.74347\" y2=\"7.74347\" stroke=\"#787878\" stroke-width=\"0.246944\" stroke-linecap=\"round\"/><rect class=\"terminal\" id=\"connector1terminal\" x=\"7.74347\" y=\"10.2835\" width=\"0.0001\" height=\"0.0001\" stroke=\"none\" stroke-width=\"0\" fill=\"none\"/><g transform=\"translate(7.37306,9.01347)\"><g transform=\"rotate(270)\"><text class=\"text\" font-family=\"'Droid Sans'\" stroke=\"none\" stroke-width=\"0\" fill=\"#8c8c8c\" font-size=\"0.881944\" x=\"0\" y=\"0\" text-anchor=\"middle\">2</text></g></g></g></svg>",
      "w": 42.51,
      "h": 39.33,
      "pins": {
        "D": [
          29.27,
          0.47
        ],
        "G": [
          0.47,
          19.67
        ],
        "S": [
          29.27,
          38.87
        ]
      }
    }
  },
  "icon": "<svg version=\"1.1\" baseProfile=\"tiny\" xmlns:svg=\"http://www.w3.org/2000/svg\" xmlns=\"http://www.w3.org/2000/svg\" x=\"0\" y=\"0\" viewBox=\"0 0 16.527 24.08\"><g id=\"breadboard\"><rect id=\"connector0pin\" x=\"0\" y=\"23\" fill=\"none\" width=\"2.16\" height=\"1\"/><rect id=\"connector1pin\" x=\"7.181\" y=\"23\" fill=\"none\" width=\"2.16\" height=\"1\"/><rect id=\"connector2pin\" x=\"14.367\" y=\"23\" fill=\"none\" width=\"2.16\" height=\"1\"/><line id=\"connector0leg\" stroke-linecap=\"round\" x1=\"1.08\" y1=\"24.08\" x2=\"1.08\" y2=\"31.259\" stroke=\"#8C8C8C\" fill=\"none\" stroke-width=\"2.16\"/><line id=\"connector1leg\" stroke-linecap=\"round\" x1=\"8.261\" y1=\"24.08\" x2=\"8.261\" y2=\"31.259\" stroke=\"#8C8C8C\" fill=\"none\" stroke-width=\"2.16\"/><line id=\"connector2leg\" stroke-linecap=\"round\" x1=\"15.447\" y1=\"24.08\" x2=\"15.447\" y2=\"31.259\" stroke=\"#8C8C8C\" fill=\"none\" stroke-width=\"2.16\"/><rect id=\"rect9506\" x=\"7.178\" y=\"14.731\" fill=\"#8C8C8C\" width=\"2.154\" height=\"9.35\"/><path id=\"path9510\" fill=\"#8C8C8C\" d=\"M3.287,14.731v3.316c0,0.424-0.782,1.059-1.198,1.425c-1.025,0.891-2.088,1.82-2.088,2.992   v1.619h2.154c0,0,0-1,0-1.209c0-0.518,0.904-1.389,1.35-1.77c0.997-0.869,1.945-1.689,1.945-2.748v-3.625H3.287L3.287,14.731z\"/><path id=\"path9514\" fill=\"#8C8C8C\" d=\"M13.221,14.731v3.316c0,0.424,0.781,1.059,1.199,1.425c1.027,0.891,2.089,1.82,2.089,2.992   v1.619h-2.154c0,0,0-1,0-1.209c0-0.518-0.904-1.389-1.35-1.77c-0.998-0.869-1.945-1.689-1.945-2.748v-3.625H13.221L13.221,14.731z\"/><rect id=\"rect9553\" x=\"1.615\" y=\"4.659\" fill=\"#1A1A1A\" width=\"13.278\" height=\"10.07\"/><path id=\"path9555\" fill=\"#141414\" d=\"M13.889,4.659v2.453v8.228v1.843c0.632-0.713,1.004-1.554,1.004-2.453l0,0V4.659H13.889z\"/><path id=\"path9557\" fill=\"#242424\" d=\"M2.621,4.659H1.616v10.07l0,0c0,0.899,0.373,1.74,1.005,2.453V15.34V7.112V4.659z\"/><path id=\"path9559\" fill=\"#1F1F1F\" d=\"M1.615,4.659L1.615,4.659c0,0.899,0.373,1.74,1.005,2.453h11.276   c0.632-0.713,1.005-1.554,1.005-2.453l0,0H1.615z\"/><path id=\"path9561\" fill=\"#141414\" d=\"M8.255,0C4.587,0,1.615,2.086,1.615,4.661h13.278C14.893,2.086,11.923,0,8.255,0z\"/><rect id=\"rect9563\" x=\"2.621\" y=\"7.112\" width=\"11.276\" height=\"10.07\"/><path fill=\"#999999\" d=\"M10.509,9.618h1.081v2.161h-1.081v1.079H7.27v1.08H5.11v-5.4h5.401L10.509,9.618L10.509,9.618z M9.43,9.618   H7.271v2.161H9.43V9.618z\"/></g></svg>"
}